{"nodes": [{"id": "web_src_lib_agent_step_limiter_ts", "label": "step-limiter.ts", "file_type": "code", "source_file": "web/src/lib/agent/step-limiter.ts", "source_location": "L1"}, {"id": "step_limiter_classifycomplexity", "label": "classifyComplexity()", "file_type": "code", "source_file": "web/src/lib/agent/step-limiter.ts", "source_location": "L44"}, {"id": "step_limiter_getsteplimit", "label": "getStepLimit()", "file_type": "code", "source_file": "web/src/lib/agent/step-limiter.ts", "source_location": "L66"}], "edges": [{"source": "web_src_lib_agent_step_limiter_ts", "target": "step_limiter_classifycomplexity", "relation": "contains", "confidence": "EXTRACTED", "source_file": "web/src/lib/agent/step-limiter.ts", "source_location": "L44", "weight": 1.0}, {"source": "web_src_lib_agent_step_limiter_ts", "target": "step_limiter_getsteplimit", "relation": "contains", "confidence": "EXTRACTED", "source_file": "web/src/lib/agent/step-limiter.ts", "source_location": "L66", "weight": 1.0}]}